{
	"pokemonName": "Hippowdon",
	"pokedexId": 450,
	"defaultFormId": 891,
	"types": [5],
	"quickMoves": [202, 240, 326, 327, 403],
	"chargedMoves": [31, 32, 131, 294, 304, 393],
	"eliteQuickMoves": [],
	"eliteChargedMoves": [],
	"genId": 4,
	"generation": "Sinnoh",
	"forms": [891],
	"sizeSettings": [
		{
			"name": "xxsLowerBound",
			"value": 0.98
		},
		{
			"name": "xsLowerBound",
			"value": 1
		},
		{
			"name": "mLowerBound",
			"value": 1.5
		},
		{
			"name": "mUpperBound",
			"value": 2.5
		},
		{
			"name": "xlUpperBound",
			"value": 3
		},
		{
			"name": "xxlUpperBound",
			"value": 3.1
		}
	],
	"attack": 201,
	"defense": 191,
	"stamina": 239,
	"height": 2,
	"weight": 300,
	"family": 449,
	"bonusCandyCapture": 2,
	"bonusStardustCapture": 200,
	"legendary": false,
	"mythic": false,
	"ultraBeast": false,
	"buddyGroupNumber": 2,
	"buddyDistance": 3,
	"thirdMoveStardust": 50000,
	"thirdMoveCandy": 50,
	"gymDefenderEligible": true,
	"tradable": true,
	"transferable": true,
	"purificationDust": 3000,
	"purificationCandy": 3
}
