{
	"pokemonName": "Mr Rime",
	"pokedexId": 866,
	"defaultFormId": 2513,
	"types": [14, 15],
	"quickMoves": [217, 234, 235],
	"chargedMoves": [30, 33, 108, 111, 391],
	"eliteQuickMoves": [],
	"eliteChargedMoves": [],
	"genId": 8,
	"generation": "Galar",
	"forms": [2513],
	"sizeSettings": [
		{
			"name": "xxsLowerBound",
			"value": 0.735
		},
		{
			"name": "xsLowerBound",
			"value": 0.75
		},
		{
			"name": "mLowerBound",
			"value": 1.125
		},
		{
			"name": "mUpperBound",
			"value": 1.875
		},
		{
			"name": "xlUpperBound",
			"value": 2.25
		},
		{
			"name": "xxlUpperBound",
			"value": 2.325
		}
	],
	"attack": 212,
	"defense": 179,
	"stamina": 190,
	"height": 1.5,
	"weight": 58.2,
	"family": 122,
	"bonusCandyCapture": 2,
	"bonusStardustCapture": 200,
	"legendary": false,
	"mythic": false,
	"ultraBeast": false,
	"buddyGroupNumber": 3,
	"buddyDistance": 5,
	"thirdMoveStardust": 75000,
	"thirdMoveCandy": 75,
	"gymDefenderEligible": true,
	"tradable": true,
	"transferable": true,
	"purificationDust": 3000,
	"purificationCandy": 3
}
