{
  "pokemonName": "Croagunk",
  "pokedexId": 453,
  "defaultFormId": 1802,
  "types": [
    2,
    4
  ],
  "quickMoves": [
    216,
    224,
    236
  ],
  "chargedMoves": [
    56,
    90,
    123
  ],
  "eliteQuickMoves": [],
  "eliteChargedMoves": [],
  "genId": 4,
  "generation": "Sinnoh",
  "forms": [
    1802
  ],
  "sizeSettings": [
    {
      "name": "xxsLowerBound",
      "value": 0.343
    },
    {
      "name": "xsLowerBound",
      "value": 0.35
    },
    {
      "name": "mLowerBound",
      "value": 0.525
    },
    {
      "name": "mUpperBound",
      "value": 0.875
    },
    {
      "name": "xlUpperBound",
      "value": 1.05
    },
    {
      "name": "xxlUpperBound",
      "value": 1.225
    }
  ],
  "attack": 116,
  "defense": 76,
  "stamina": 134,
  "height": 0.7,
  "weight": 23,
  "family": 453,
  "legendary": false,
  "mythic": false,
  "ultraBeast": false,
  "buddyGroupNumber": 2,
  "buddyDistance": 3,
  "thirdMoveStardust": 50000,
  "thirdMoveCandy": 50,
  "gymDefenderEligible": true,
  "tradable": true,
  "transferable": true,
  "evolutions": [
    {
      "evoId": 454,
      "candyCost": 50
    }
  ],
  "costumeOverrideEvos": [
    {
      "costumeId": 16,
      "costumeProto": "FALL_2020_NOEVOLVE",
      "costumeName": "Fall 2020 Noevolve"
    }
  ],
  "purificationDust": 3000,
  "purificationCandy": 3
}