{
  "pokemonName": "Pineco",
  "pokedexId": 204,
  "defaultFormId": 1244,
  "types": [
    7
  ],
  "quickMoves": [
    201,
    221
  ],
  "chargedMoves": [
    63,
    258,
    267
  ],
  "eliteQuickMoves": [],
  "eliteChargedMoves": [],
  "genId": 2,
  "generation": "Johto",
  "forms": [
    1244
  ],
  "sizeSettings": [
    {
      "name": "xxsLowerBound",
      "value": 0.2989
    },
    {
      "name": "xsLowerBound",
      "value": 0.305
    },
    {
      "name": "mLowerBound",
      "value": 0.4575
    },
    {
      "name": "mUpperBound",
      "value": 0.7625
    },
    {
      "name": "xlUpperBound",
      "value": 0.915
    },
    {
      "name": "xxlUpperBound",
      "value": 1.0675
    }
  ],
  "attack": 108,
  "defense": 122,
  "stamina": 137,
  "height": 0.61,
  "weight": 7.2,
  "family": 204,
  "legendary": false,
  "mythic": false,
  "ultraBeast": false,
  "buddyGroupNumber": 2,
  "buddyDistance": 5,
  "thirdMoveStardust": 75000,
  "thirdMoveCandy": 75,
  "gymDefenderEligible": true,
  "tradable": true,
  "transferable": true,
  "evolutions": [
    {
      "evoId": 205,
      "formId": 1247,
      "candyCost": 50
    }
  ],
  "purificationDust": 5000,
  "purificationCandy": 5
}