{
  "pokemonName": "Carvanha",
  "pokedexId": 318,
  "defaultFormId": 734,
  "types": [
    11,
    17
  ],
  "quickMoves": [
    202,
    278
  ],
  "chargedMoves": [
    50,
    57,
    279
  ],
  "eliteQuickMoves": [],
  "eliteChargedMoves": [],
  "genId": 3,
  "generation": "Hoenn",
  "forms": [
    734
  ],
  "sizeSettings": [
    {
      "name": "xxsLowerBound",
      "value": 0.3871
    },
    {
      "name": "xsLowerBound",
      "value": 0.395
    },
    {
      "name": "mLowerBound",
      "value": 0.5925
    },
    {
      "name": "mUpperBound",
      "value": 0.9875
    },
    {
      "name": "xlUpperBound",
      "value": 1.185
    },
    {
      "name": "xxlUpperBound",
      "value": 1.58
    }
  ],
  "attack": 171,
  "defense": 39,
  "stamina": 128,
  "height": 0.79,
  "weight": 20.8,
  "family": 318,
  "legendary": false,
  "mythic": false,
  "ultraBeast": false,
  "buddyGroupNumber": 3,
  "buddyDistance": 3,
  "buddyMegaEnergy": 15,
  "thirdMoveStardust": 50000,
  "thirdMoveCandy": 50,
  "gymDefenderEligible": true,
  "tradable": true,
  "transferable": true,
  "evolutions": [
    {
      "evoId": 319,
      "formId": 737,
      "candyCost": 50
    }
  ],
  "purificationDust": 3000,
  "purificationCandy": 3
}